tflite_token_sync/__init__.py
tflite_token_sync/tflite_token_sync.py
tflite_token_sync/__pycache__/__init__.cpython-39.pyc
tflite_token_sync/__pycache__/tflite_token_sync.cpython-39.pyc
tflite_token_sync-0.1.2.dist-info/LICENSE
tflite_token_sync-0.1.2.dist-info/METADATA
tflite_token_sync-0.1.2.dist-info/WHEEL
tflite_token_sync-0.1.2.dist-info/entry_points.txt
tflite_token_sync-0.1.2.dist-info/top_level.txt
tflite_token_sync-0.1.2.dist-info/RECORD
