Metadata-Version: 2.2
Name: tflite-token-sync
Version: 0.1.2
Summary: A utility tool to synchronize caching tokens among multiple TensorFlow Lite models
Author-email: Changhun Han <ehwjs1914@naver.com>
License: MIT
Project-URL: Homepage, https://github.com/HanChangHun/tflite-token-sync
Project-URL: Repository, https://github.com/HanChangHun/tflite-token-sync
Project-URL: Issues, https://github.com/HanChangHun/tflite-token-sync/issues
Keywords: TFLite,EdgeTPU,caching,token,synchronizer
Classifier: Programming Language :: Python :: 3
Classifier: Operating System :: OS Independent
Classifier: License :: OSI Approved :: MIT License
Classifier: Topic :: Software Development :: Libraries :: Python Modules
Classifier: Intended Audience :: Developers
Requires-Python: >=3.7
License-File: LICENSE
Requires-Dist: flatbuffers
